HABZONEpy/__init__.py
HABZONEpy/zohab.py
HABZONEpy-1.0.3.dist-info/LICENSE
HABZONEpy-1.0.3.dist-info/METADATA
HABZONEpy-1.0.3.dist-info/WHEEL
HABZONEpy-1.0.3.dist-info/top_level.txt
HABZONEpy-1.0.3.dist-info/RECORD
