Metadata-Version: 2.1
Name: HABZONEpy
Version: 1.0.3
Summary: codigo para visualizar y encontrar la zona habitable
Home-page: https://github.com/nachowo21/HABZONEpy.git
Author: Ignacio Solís, Joaquin Lopez, Ignacio Cordova
License: MIT
License-File: LICENSE
Requires-Dist: numpy
Requires-Dist: matplotlib
